environment_file/__init__.py
environment_file/environment_file.py
environment_file-1.0.0.dist-info/DESCRIPTION.rst
environment_file-1.0.0.dist-info/METADATA
environment_file-1.0.0.dist-info/RECORD
environment_file-1.0.0.dist-info/WHEEL
environment_file-1.0.0.dist-info/metadata.json
environment_file-1.0.0.dist-info/top_level.txt
environment_file-1.0.0.dist-info/zip-safe
