Metadata-Version: 2.0
Name: environment-file
Version: 1.0.0
Summary: 
